imgseg/__init__.py
imgseg/image_processor
imgseg/run.py
imgseg-0.0.1.dist-info/METADATA
imgseg-0.0.1.dist-info/WHEEL
imgseg-0.0.1.dist-info/top_level.txt
imgseg-0.0.1.dist-info/RECORD
