Metadata-Version: 2.1
Name: imgseg
Version: 0.0.1
Summary: Package for line segmentation
Author: LugandaOCR
Author-email: beijukab@gmail.com
License: MIT
Requires-Dist: numpy
Requires-Dist: opencv-python-headless
